[
    {
        "firstName": "ali",
        "lastName": "mohd",
        "email": "mohd@mgmail.com",
        "password": "$2b$10$c7TAaDIH3D9pHMzCzFsbOeNacSnruYCy1CGZUQoXe7cheaDvpE8OS",
        "phonenumber": "7876745635",
        "address": "hyd",
        "task": []
    },
    {
        "firstName": "suhail",
        "lastName": "roushan",
        "email": "suhail@code.in",
        "password": "$2b$10$iiZEFcSNMftVr0pGyw2ly.wfPwBsb9qdtvN.B82LJkZNqvVhhosOe",
        "phonenumber": "6374654657",
        "address": "hyd",
        "task": []
    },
    {
        "firstName": "hanzala",
        "lastName": "shaik",
        "email": "shaikhhanzala27@gmail.com",
        "password": "$2b$10$myucvXgkL3yNeS3lUnNPuuX53z25yFRiY8KuJTiIUx.f059daNBpa",
        "phonenumber": "7564536267",
        "address": "hyd",
        "task": []
    }
]